pyunxiao/__init__.py
pyunxiao/main.py
pyunxiao-0.0.1.dist-info/DESCRIPTION.rst
pyunxiao-0.0.1.dist-info/METADATA
pyunxiao-0.0.1.dist-info/RECORD
pyunxiao-0.0.1.dist-info/WHEEL
pyunxiao-0.0.1.dist-info/metadata.json
pyunxiao-0.0.1.dist-info/top_level.txt
pyunxiao-0.0.1.dist-info/zip-safe
